{"atividade_principal": [{"text": "Fabrica\u00e7\u00e3o de materiais para medicina e odontologia", "code": "32.50-7-05"}], "data_situacao": "03/11/2005", "nome": "FANEM LTDA", "uf": "SP", "telefone": "(11) 2465-2199/ (11) 2972-5700", "email": "fiscal@fanem.com.br", "atividades_secundarias": [{"text": "Aluguel de outras m\u00e1quinas e equipamentos comerciais e industriais n\u00e3o especificados anteriormente, sem operador", "code": "77.39-0-99"}, {"text": "Atividades de intermedia\u00e7\u00e3o e agenciamento de servi\u00e7os e neg\u00f3cios em geral, exceto imobili\u00e1rios", "code": "74.90-1-04"}, {"text": "Com\u00e9rcio atacadista de M\u00e1quinas e equipamentos para uso industrial; partes e pe\u00e7as", "code": "46.63-0-00"}, {"text": "Fabrica\u00e7\u00e3o de instrumentos n\u00e3o-eletr\u00f4nicos e utens\u00edlios para uso m\u00e9dico, cir\u00fargico, odontol\u00f3gico e de laborat\u00f3rio", "code": "32.50-7-01"}, {"text": "Aluguel de equipamentos cient\u00edficos, m\u00e9dicos e hospitalares, sem operador", "code": "77.39-0-02"}, {"text": "Fabrica\u00e7\u00e3o de aparelhos eletrom\u00e9dicos e eletroterap\u00eauticos e equipamentos de irradia\u00e7\u00e3o", "code": "26.60-4-00"}, {"text": "Manuten\u00e7\u00e3o e repara\u00e7\u00e3o de aparelhos eletrom\u00e9dicos e eletroterap\u00eauticos e equipamentos de irradia\u00e7\u00e3o", "code": "33.12-1-03"}, {"text": "Manuten\u00e7\u00e3o e repara\u00e7\u00e3o de m\u00e1quinas e equipamentos para uso geral n\u00e3o especificados anteriormente", "code": "33.14-7-10"}], "qsa": [{"qual": "49-S\u00f3cio-Administrador", "nome": "DJALMA LUIZ RODRIGUES"}, {"qual": "37-S\u00f3cio Pessoa Jur\u00eddica Domiciliado no Exterior", "pais_origem": "ESTADOS UNIDOS", "nome_rep_legal": "CLAUDIO MAURICIO FREDDO", "qual_rep_legal": "17-Procurador", "nome": "DRAEGER MEDICAL, INC."}], "situacao": "ATIVA", "bairro": "CUMBICA", "logradouro": "R ARTHUR CARL SCHMIDT", "numero": "186", "cep": "07.222-050", "municipio": "GUARULHOS", "porte": "DEMAIS", "abertura": "18/07/1966", "natureza_juridica": "206-2 - Sociedade Empres\u00e1ria Limitada", "fantasia": "FANEM LTDA", "cnpj": "61.100.244/0001-30", "ultima_atualizacao": "2020-02-07T23:13:05.175Z", "status": "OK", "tipo": "MATRIZ", "complemento": "", "efr": "", "motivo_situacao": "", "situacao_especial": "", "data_situacao_especial": "", "capital_social": "23310070.00", "extra": {}, "billing": {"free": false, "database": true}}