{"data_situacao": "31/12/2017", "motivo_situacao": "INCORPORACAO", "nome": "DPZ DUAILIBI PETIT ZARAGOZA PROPAGANDA LTDA.", "telefone": "(11) 4949-0700", "email": "tributario@br-resources.com", "situacao": "BAIXADA", "porte": "DEMAIS", "abertura": "11/02/1972", "natureza_juridica": "206-2 - Sociedade Empres\u00e1ria Limitada", "cnpj": "62.123.948/0002-72", "ultima_atualizacao": "2020-02-08T01:00:27.121Z", "status": "OK", "tipo": "FILIAL", "fantasia": "", "logradouro": "", "numero": "", "complemento": "", "cep": "", "bairro": "", "municipio": "", "uf": "", "efr": "", "situacao_especial": "", "data_situacao_especial": "", "atividade_principal": [{"code": "00.00-0-00", "text": "********"}], "atividades_secundarias": [{"code": "00.00-0-00", "text": "N\u00e3o informada"}], "capital_social": "0.00", "qsa": [], "extra": {}, "billing": {"free": false, "database": true}}