{"data_situacao": "01/02/2018", "motivo_situacao": "REGISTRO CANCELADO", "nome": "MARCELO MANHAES DE OLIVEIRA 01763144747", "telefone": "(22) 9838-6048", "situacao": "BAIXADA", "porte": "MICRO EMPRESA", "abertura": "12/12/2011", "natureza_juridica": "213-5 - Empres\u00e1rio (Individual)", "cnpj": "14.749.668/0001-40", "ultima_atualizacao": "2020-02-08T00:35:16.071Z", "status": "OK", "tipo": "MATRIZ", "fantasia": "", "logradouro": "", "numero": "", "complemento": "", "cep": "", "bairro": "", "municipio": "", "uf": "", "email": "", "efr": "", "situacao_especial": "", "data_situacao_especial": "", "atividade_principal": [{"code": "00.00-0-00", "text": "********"}], "atividades_secundarias": [{"code": "00.00-0-00", "text": "N\u00e3o informada"}], "capital_social": "0.00", "qsa": [], "extra": {}, "billing": {"free": false, "database": false}}