{"atividade_principal": [{"text": "Seguridade social obrigat\u00f3ria", "code": "84.30-2-00"}], "data_situacao": "26/12/2003", "nome": "OSTRASPREV - RIO DAS OSTRAS PREVIDENCIA", "efr": "MUNIC\u00cdPIO DE RIO DAS OSTRAS", "uf": "RJ", "telefone": "(22) 2764-1310/ (22) 2764-1198", "email": "ipasro@gmail.com", "situacao": "ATIVA", "bairro": "EXTENSAO DO BOSQUE", "logradouro": "R RIO GRANDE DO SUL", "numero": "129", "cep": "28.890-001", "municipio": "RIO DAS OSTRAS", "porte": "DEMAIS", "abertura": "21/02/1994", "natureza_juridica": "112-0 - Autarquia Municipal", "fantasia": "OSTRASPREV", "cnpj": "39.691.605/0001-01", "ultima_atualizacao": "2020-02-07T23:18:33.997Z", "status": "OK", "tipo": "MATRIZ", "complemento": "", "motivo_situacao": "", "situacao_especial": "", "data_situacao_especial": "", "atividades_secundarias": [{"code": "00.00-0-00", "text": "N\u00e3o informada"}], "capital_social": "0.00", "qsa": [], "extra": {}, "billing": {"free": false, "database": false}}