{"atividade_principal": [{"text": "Fabrica\u00e7\u00e3o de instrumentos n\u00e3o-eletr\u00f4nicos e utens\u00edlios para uso m\u00e9dico, cir\u00fargico, odontol\u00f3gico e de laborat\u00f3rio", "code": "32.50-7-01"}], "data_situacao": "03/11/2005", "nome": "MACOM INSTRUMENTAL CIRURGICO INDUSTRIA LTDA", "uf": "SP", "telefone": "(11) 2431-4636", "email": "rubens@maconinstrumental.com.br", "atividades_secundarias": [{"text": "Fabrica\u00e7\u00e3o de aparelhos eletrom\u00e9dicos e eletroterap\u00eauticos e equipamentos de irradia\u00e7\u00e3o", "code": "26.60-4-00"}, {"text": "Aluguel de equipamentos cient\u00edficos, m\u00e9dicos e hospitalares, sem operador", "code": "77.39-0-02"}, {"text": "Manuten\u00e7\u00e3o e repara\u00e7\u00e3o de equipamentos e produtos n\u00e3o especificados anteriormente", "code": "33.19-8-00"}], "qsa": [{"qual": "22-S\u00f3cio", "nome": "RUBENS RODRIGUES DOS SANTOS"}, {"qual": "49-S\u00f3cio-Administrador", "nome": "REINALDO RODRIGUES DOS SANTOS"}], "situacao": "ATIVA", "bairro": "PARQUE INDUSTRIAL FERREIRA FERNANDES", "logradouro": "AV JOAO BASSI", "numero": "572", "cep": "07.174-460", "municipio": "GUARULHOS", "porte": "DEMAIS", "abertura": "01/11/1993", "natureza_juridica": "206-2 - Sociedade Empres\u00e1ria Limitada", "cnpj": "59.650.556/0001-76", "ultima_atualizacao": "2020-02-08T00:25:10.998Z", "status": "OK", "tipo": "MATRIZ", "fantasia": "", "complemento": "", "efr": "", "motivo_situacao": "", "situacao_especial": "", "data_situacao_especial": "", "capital_social": "2000000.00", "extra": {}, "billing": {"free": false, "database": true}}